hardsync/__init__.py
hardsync/__main__.py
hardsync/channels.py
hardsync/clients.py
hardsync/defaults.py
hardsync/discovery.py
hardsync/dynamics.py
hardsync/encodings.py
hardsync/example/__init__.py
hardsync/example/contract.py
hardsync/example/requesting_application.py
hardsync/generators/__init__.py
hardsync/generators/arduino/__init__.py
hardsync/generators/arduino/arduino.py
hardsync/generators/arduino/templates/client.cpp
hardsync/generators/arduino/templates/client.h
hardsync/generators/arduino/templates/firmware.ino
hardsync/generators/arduino/templates/parser.cpp
hardsync/generators/arduino/templates/parser.h
hardsync/generators/arduino/templates/sketch_desired.ino
hardsync/generators/arduino/test_arduino.py
hardsync/generators/arduino/test_data/client.cpp
hardsync/generators/arduino/test_data/client.h
hardsync/generators/arduino/test_data/contract.py
hardsync/generators/arduino/test_data/firmware.ino
hardsync/generators/arduino/test_data/parser.cpp
hardsync/generators/arduino/test_data/parser.h
hardsync/generators/common.py
hardsync/generators/python/__init__.py
hardsync/generators/python/python.py
hardsync/generators/python/templates/__init__.py
hardsync/generators/python/templates/application.py
hardsync/generators/python/templates/client.py
hardsync/generators/python/test_data/client.py
hardsync/generators/python/test_python.py
hardsync/generators/test_common.py
hardsync/interfaces.py
hardsync/tests/__init__.py
hardsync/tests/test_client.py
hardsync/tests/test_data/__init__.py
hardsync/tests/test_data/bad_contracts/complex_type.py
hardsync/tests/test_data/bad_contracts/missing_type.py
hardsync/tests/test_data/good_contracts/empty.py
hardsync/tests/test_data/good_contracts/empty_request.py
hardsync/tests/test_data/good_contracts/empty_response.py
hardsync/tests/test_data/good_contracts/missing_request.py
hardsync/tests/test_data/good_contracts/missing_response.py
hardsync/tests/test_data/good_contracts/single_action.py
hardsync-0.5.0.dist-info/METADATA
hardsync-0.5.0.dist-info/WHEEL
hardsync-0.5.0.dist-info/RECORD
