Metadata-Version: 2.1
Name: hardsync
Version: 0.5.0
Summary: Hardware / software communication made easy
License: MIT
Author: Jordan Edmunds
Requires-Python: >=3.10,<4.0
Classifier: License :: OSI Approved :: MIT License
Classifier: Programming Language :: Python :: 3
Classifier: Programming Language :: Python :: 3.10
Classifier: Programming Language :: Python :: 3.11
Requires-Dist: click (>=8.1.7,<9.0.0)
Requires-Dist: pyserial (>=3.5,<4.0)
Requires-Dist: pyserial-asyncio (>=0.6,<0.7)
